MANIFEST.in
README.md
setup.py
mritopng/__init__.py
mritopng/__main__.py
mritopng/contrast.py
mritopng/models.py
mritopng.egg-info/PKG-INFO
mritopng.egg-info/SOURCES.txt
mritopng.egg-info/dependency_links.txt
mritopng.egg-info/entry_points.txt
mritopng.egg-info/not-zip-safe
mritopng.egg-info/requires.txt
mritopng.egg-info/top_level.txt