Metadata-Version: 1.1
Name: mritopng
Version: 2.2
Summary: Easily convert MRI filed based on the DICOM format to a PNG image
Home-page: https://github.com/danishm/mritopng
Author: Danish Mujeeb
Author-email: danish@dsharpapps.com
License: MIT
Platform: UNKNOWN
Classifier: Development Status :: 4 - Beta
Classifier: License :: OSI Approved :: MIT License
Classifier: Programming Language :: Python :: 3
Classifier: Topic :: Multimedia :: Graphics :: Graphics Conversion
Classifier: Environment :: Console
Classifier: Intended Audience :: Healthcare Industry
Classifier: Intended Audience :: End Users/Desktop
